cv_datetime_utils/__init__.py
cv_datetime_utils/core.py
wf_cv_datetime_utils-0.1.0.dist-info/LICENSE
wf_cv_datetime_utils-0.1.0.dist-info/METADATA
wf_cv_datetime_utils-0.1.0.dist-info/WHEEL
wf_cv_datetime_utils-0.1.0.dist-info/top_level.txt
wf_cv_datetime_utils-0.1.0.dist-info/RECORD
